LICENSE
README.md
setup.cfg
setup.py
pytimize/__init__.py
pytimize.egg-info/PKG-INFO
pytimize.egg-info/SOURCES.txt
pytimize.egg-info/dependency_links.txt
pytimize.egg-info/not-zip-safe
pytimize.egg-info/requires.txt
pytimize.egg-info/top_level.txt
pytimize/formulations/__init__.py
pytimize/formulations/integer/__init__.py
pytimize/formulations/integer/_abstract.py
pytimize/formulations/integer/_objective.py
pytimize/formulations/linear/__init__.py
pytimize/formulations/linear/_abstract.py
pytimize/formulations/linear/_constraint.py
pytimize/formulations/linear/_equation.py
pytimize/formulations/linear/_objective.py
pytimize/formulations/linear/_utilities.py
pytimize/formulations/linear/_variable.py
pytimize/graphs/__init__.py
pytimize/graphs/_directed.py
pytimize/graphs/_undirected.py
pytimize/parsers/__init__.py
pytimize/parsers/_description.py
pytimize/parsers/_graph.py
pytimize/parsers/_linear.py
pytimize/parsers/_symbol.py
pytimize/programs/__init__.py
pytimize/programs/_integer.py
pytimize/programs/_linear.py
pytimize/programs/_nonlinear.py
pytimize/programs/_unconstrained.py
pytimize/utilities/__init__.py
pytimize/utilities/_comparator.py
pytimize/utilities/_disjoint.py