Metadata-Version: 2.1
Name: pytimize
Version: 0.0.4
Summary: Python optimization library for mathematical programming.
Home-page: https://pytimize.terrytm.com
Author: Terry Zheng et al.
Author-email: pytimize@terrytm.com
Maintainer: Pytimize Developers
Maintainer-email: pytimize@terrytm.com
License: Apache 2.0
Project-URL: Bug Reports, https://pytimize.terrytm.com/issues
Project-URL: Documentation, https://pytimize.terrytm.com
Project-URL: Source Code, https://github.com/TerrayTM/pytimize
Keywords: mathematical programming optimization
Platform: UNKNOWN
Classifier: Development Status :: 2 - Pre-Alpha
Classifier: Intended Audience :: Science/Research
Classifier: Intended Audience :: Developers
Classifier: Intended Audience :: Education
Classifier: License :: OSI Approved :: Apache Software License
Classifier: Programming Language :: Python
Classifier: Programming Language :: Python :: 3.8
Classifier: Topic :: Software Development
Classifier: Topic :: Scientific/Engineering
Classifier: Operating System :: OS Independent
Requires-Python: >=3.8
License-File: LICENSE
